session1/__init__.py
session1/class_to_test.py
session1/example_with_pandas.py
session1/functions.py
session1/run.py
session1/test_test.py
session1/testing_logging.py
session2/__init__.py
session2/exercise1/__init__.py
session2/exercise1/calculate_power_module.py
session2/exercise1/calculate_square_root_module.py
session2/exercise1/count_letters_module.py
session2/exercise1/run.py
session2/exercise2/__init__.py
session2/exercise2/cars/__init__.py
session2/exercise2/cars/bmw.py
session2/exercise2/cars/mercedes.py
session2/exercise2/cars/renault.py
session2/exercise2/cars/sample.py
session2/exercise2/shopping/__init__.py
session2/exercise2/shopping/car_list.py
David_carlist-0.0.1.dist-info/METADATA
David_carlist-0.0.1.dist-info/WHEEL
David_carlist-0.0.1.dist-info/top_level.txt
David_carlist-0.0.1.dist-info/RECORD
